cmakestrap/__init__.py
cmakestrap/__main__.py
cmakestrap/__version__.py
cmakestrap/cli.py
cmakestrap/templates/__init__.py
cmakestrap/templates/cmake/fetch.cmake.in
cmakestrap/templates/cmake/lib.cmake.in
cmakestrap/templates/cmake/main.cmake.in
cmakestrap/templates/cmake/module.cmake.in
cmakestrap/templates/cmake/mold.cmake.in
cmakestrap/templates/cmake/prelude.cmake.in
cmakestrap/templates/conan/conanfile.py.in
cmakestrap/templates/cpp/lib-no-fmt.hpp.in
cmakestrap/templates/cpp/lib.cxx.in
cmakestrap/templates/cpp/lib.hpp.in
cmakestrap/templates/cpp/main.cpp.in
cmakestrap/templates/cpp/main.cxx.in
cmakestrap/templates/git/.gitignore.in
cmakestrap-0.2.0.dist-info/METADATA
cmakestrap-0.2.0.dist-info/WHEEL
cmakestrap-0.2.0.dist-info/entry_points.txt
cmakestrap-0.2.0.dist-info/licenses/LICENSE
cmakestrap-0.2.0.dist-info/RECORD
