Metadata-Version: 2.4
Name: cmakestrap
Version: 0.2.0
Summary: Simpler CMake project initializer script for C++
Project-URL: Repository, https://github.com/mrizaln/cmakestrap
Project-URL: Issues, https://github.com/mrizaln/cmakestrap/issues
Author-email: Muhammad Rizal Nurromdhoni <mrizaln2000@gmail.com>
Maintainer-email: Muhammad Rizal Nurromdhoni <mrizaln2000@gmail.com>
License-Expression: MIT
License-File: LICENSE
Keywords: c++,cmake,init
Classifier: Development Status :: 3 - Alpha
Classifier: Intended Audience :: Developers
Classifier: License :: OSI Approved :: MIT License
Classifier: Natural Language :: English
Classifier: Operating System :: OS Independent
Classifier: Programming Language :: C++
Classifier: Programming Language :: Python :: 3
Classifier: Topic :: Software Development
Requires-Python: >=3.12
